g2s/__init__.py
g2s/g2s.cpython-311-darwin.so
G2S-0.98.21.dist-info/METADATA
G2S-0.98.21.dist-info/WHEEL
G2S-0.98.21.dist-info/top_level.txt
G2S-0.98.21.dist-info/RECORD
