Metadata-Version: 2.1
Name: G2S
Version: 0.98.21
Summary: G2S interface
Home-page: https://github.com/GAIA-UNIL/G2S
Author: Mathieu Gravey
Author-email: g2s@mgravey.com
License: GPLv3
Classifier: Development Status :: 4 - Beta
Classifier: Intended Audience :: Science/Research
Classifier: Intended Audience :: Education
Classifier: License :: OSI Approved :: GNU Lesser General Public License v3 (LGPLv3)
Classifier: Programming Language :: C++
Classifier: Programming Language :: Python :: 3 :: Only
Requires-Dist: numpy
